qnicorn/__init__.py
qnicorn/arm64_const.py
qnicorn/arm_const.py
qnicorn/m68k_const.py
qnicorn/mips_const.py
qnicorn/ppc_const.py
qnicorn/qnicorn.py
qnicorn/qnicorn_const.py
qnicorn/riscv_const.py
qnicorn/sparc_const.py
qnicorn/uc_const.py
qnicorn/x86_const.py
qnicorn/include/qnicorn/arm.h
qnicorn/include/qnicorn/arm64.h
qnicorn/include/qnicorn/m68k.h
qnicorn/include/qnicorn/mips.h
qnicorn/include/qnicorn/platform.h
qnicorn/include/qnicorn/ppc.h
qnicorn/include/qnicorn/qnicorn.h
qnicorn/include/qnicorn/riscv.h
qnicorn/include/qnicorn/sparc.h
qnicorn/include/qnicorn/x86.h
qnicorn/lib/libqnicorn.so
qnicorn-1.0.0.post1.dist-info/METADATA
qnicorn-1.0.0.post1.dist-info/WHEEL
qnicorn-1.0.0.post1.dist-info/top_level.txt
qnicorn-1.0.0.post1.dist-info/RECORD
