Metadata-Version: 2.1
Name: qnicorn
Version: 1.0.0.post1
Summary: Qnicorn Enmulation Engine
Home-page: http://www.qnicorn.org
Author: Lazymio
Author-email: mio@lazym.io
License: UNKNOWN
Platform: UNKNOWN
Classifier: License :: OSI Approved :: BSD License
Classifier: Programming Language :: Python :: 2
Classifier: Programming Language :: Python :: 3
Requires: ctypes
Provides: qnicorn
